{
	"completely_empty": false,
	"image": {
		"height": 480,
		"scale": 1.6458333333333333,
		"width": 640
	},
	"mark": [
		{
			"class_idx": 5,
			"name": "arrow",
			"points": [
				{
					"int_x": 119,
					"int_y": 231,
					"x": 0.18593750000000003,
					"y": 0.48125000000000007
				},
				{
					"int_x": 248,
					"int_y": 231,
					"x": 0.3875,
					"y": 0.48125000000000007
				},
				{
					"int_x": 248,
					"int_y": 357,
					"x": 0.3875,
					"y": 0.74375
				},
				{
					"int_x": 119,
					"int_y": 357,
					"x": 0.18593750000000003,
					"y": 0.74375
				}
			],
			"rect": {
				"h": 0.26249999999999996,
				"int_h": 127,
				"int_w": 130,
				"int_x": 119,
				"int_y": 231,
				"w": 0.20156249999999998,
				"x": 0.18593750000000003,
				"y": 0.48125000000000007
			}
		}
	],
	"timestamp": 1640750989,
	"version": "1.5.30-1"
}
