{
	"completely_empty": false,
	"image": {
		"height": 480,
		"scale": 1.6458333333333333,
		"width": 640
	},
	"mark": [
		{
			"class_idx": 5,
			"name": "arrow",
			"points": [
				{
					"int_x": 108,
					"int_y": 46,
					"x": 0.16875,
					"y": 0.09583333333333333
				},
				{
					"int_x": 213,
					"int_y": 46,
					"x": 0.3328125,
					"y": 0.09583333333333333
				},
				{
					"int_x": 213,
					"int_y": 180,
					"x": 0.3328125,
					"y": 0.375
				},
				{
					"int_x": 108,
					"int_y": 180,
					"x": 0.16875,
					"y": 0.375
				}
			],
			"rect": {
				"h": 0.2791666666666667,
				"int_h": 135,
				"int_w": 106,
				"int_x": 108,
				"int_y": 46,
				"w": 0.1640625,
				"x": 0.16875,
				"y": 0.09583333333333333
			}
		}
	],
	"timestamp": 1640750989,
	"version": "1.5.30-1"
}
