{
	"completely_empty": false,
	"image": {
		"height": 480,
		"scale": 1.6458333333333333,
		"width": 640
	},
	"mark": [
		{
			"class_idx": 1,
			"name": "circle",
			"points": [
				{
					"int_x": 115,
					"int_y": 328,
					"x": 0.18046874999999998,
					"y": 0.6822916666666666
				},
				{
					"int_x": 238,
					"int_y": 328,
					"x": 0.37109375,
					"y": 0.6822916666666666
				},
				{
					"int_x": 238,
					"int_y": 450,
					"x": 0.37109375,
					"y": 0.9364583333333333
				},
				{
					"int_x": 115,
					"int_y": 450,
					"x": 0.18046874999999998,
					"y": 0.9364583333333333
				}
			],
			"rect": {
				"h": 0.25416666666666665,
				"int_h": 123,
				"int_w": 124,
				"int_x": 115,
				"int_y": 328,
				"w": 0.19062500000000002,
				"x": 0.18046874999999998,
				"y": 0.6822916666666666
			}
		}
	],
	"timestamp": 1640750989,
	"version": "1.5.30-1"
}
