{
	"completely_empty": false,
	"image": {
		"height": 480,
		"scale": 1.6458333333333333,
		"width": 640
	},
	"mark": [
		{
			"class_idx": 3,
			"name": "rectangle",
			"points": [
				{
					"int_x": 298,
					"int_y": 40,
					"x": 0.46562500000000007,
					"y": 0.08333333333333331
				},
				{
					"int_x": 536,
					"int_y": 40,
					"x": 0.8375,
					"y": 0.08333333333333331
				},
				{
					"int_x": 536,
					"int_y": 165,
					"x": 0.8375,
					"y": 0.34375
				},
				{
					"int_x": 298,
					"int_y": 165,
					"x": 0.46562500000000007,
					"y": 0.34375
				}
			],
			"rect": {
				"h": 0.2604166666666667,
				"int_h": 126,
				"int_w": 239,
				"int_x": 298,
				"int_y": 40,
				"w": 0.37187499999999996,
				"x": 0.46562500000000007,
				"y": 0.08333333333333331
			}
		}
	],
	"timestamp": 1640750995,
	"version": "1.5.30-1"
}
