{
	"completely_empty": false,
	"image": {
		"height": 480,
		"scale": 1.6458333333333333,
		"width": 640
	},
	"mark": [
		{
			"class_idx": 2,
			"name": "square",
			"points": [
				{
					"int_x": 421,
					"int_y": 221,
					"x": 0.6578125,
					"y": 0.46041666666666664
				},
				{
					"int_x": 553,
					"int_y": 221,
					"x": 0.8640625000000001,
					"y": 0.46041666666666664
				},
				{
					"int_x": 553,
					"int_y": 353,
					"x": 0.8640625000000001,
					"y": 0.7354166666666666
				},
				{
					"int_x": 421,
					"int_y": 353,
					"x": 0.6578125,
					"y": 0.7354166666666666
				}
			],
			"rect": {
				"h": 0.27499999999999997,
				"int_h": 133,
				"int_w": 133,
				"int_x": 421,
				"int_y": 221,
				"w": 0.20625000000000004,
				"x": 0.6578125,
				"y": 0.46041666666666664
			}
		}
	],
	"timestamp": 1640750996,
	"version": "1.5.30-1"
}
