{
	"completely_empty": false,
	"image": {
		"height": 480,
		"scale": 1.6458333333333333,
		"width": 640
	},
	"mark": [
		{
			"class_idx": 2,
			"name": "square",
			"points": [
				{
					"int_x": 192,
					"int_y": 299,
					"x": 0.3,
					"y": 0.6229166666666667
				},
				{
					"int_x": 331,
					"int_y": 299,
					"x": 0.5171875,
					"y": 0.6229166666666667
				},
				{
					"int_x": 331,
					"int_y": 438,
					"x": 0.5171875,
					"y": 0.9125
				},
				{
					"int_x": 192,
					"int_y": 438,
					"x": 0.3,
					"y": 0.9125
				}
			],
			"rect": {
				"h": 0.2895833333333333,
				"int_h": 140,
				"int_w": 140,
				"int_x": 192,
				"int_y": 299,
				"w": 0.21718750000000003,
				"x": 0.3,
				"y": 0.6229166666666667
			}
		}
	],
	"timestamp": 1640750996,
	"version": "1.5.30-1"
}
