{
	"completely_empty": false,
	"image": {
		"height": 480,
		"scale": 1.6458333333333333,
		"width": 640
	},
	"mark": [
		{
			"class_idx": 2,
			"name": "square",
			"points": [
				{
					"int_x": 23,
					"int_y": 129,
					"x": 0.0359375,
					"y": 0.26875
				},
				{
					"int_x": 157,
					"int_y": 129,
					"x": 0.2453125,
					"y": 0.26875
				},
				{
					"int_x": 157,
					"int_y": 263,
					"x": 0.2453125,
					"y": 0.5479166666666666
				},
				{
					"int_x": 23,
					"int_y": 263,
					"x": 0.0359375,
					"y": 0.5479166666666666
				}
			],
			"rect": {
				"h": 0.2791666666666666,
				"int_h": 135,
				"int_w": 135,
				"int_x": 23,
				"int_y": 129,
				"w": 0.20937499999999998,
				"x": 0.0359375,
				"y": 0.26875
			}
		}
	],
	"timestamp": 1640750996,
	"version": "1.5.30-1"
}
