{
	"completely_empty": false,
	"image": {
		"height": 480,
		"scale": 1.6458333333333333,
		"width": 640
	},
	"mark": [
		{
			"class_idx": 6,
			"name": "triangle",
			"points": [
				{
					"int_x": 173,
					"int_y": 83,
					"x": 0.27031249999999996,
					"y": 0.17291666666666666
				},
				{
					"int_x": 290,
					"int_y": 83,
					"x": 0.453125,
					"y": 0.17291666666666666
				},
				{
					"int_x": 290,
					"int_y": 219,
					"x": 0.453125,
					"y": 0.45625
				},
				{
					"int_x": 173,
					"int_y": 219,
					"x": 0.27031249999999996,
					"y": 0.45625
				}
			],
			"rect": {
				"h": 0.2833333333333333,
				"int_h": 137,
				"int_w": 118,
				"int_x": 173,
				"int_y": 83,
				"w": 0.18281250000000004,
				"x": 0.27031249999999996,
				"y": 0.17291666666666666
			}
		}
	],
	"timestamp": 1640750997,
	"version": "1.5.30-1"
}
