{
	"completely_empty": false,
	"image": {
		"height": 480,
		"scale": 1.6458333333333333,
		"width": 640
	},
	"mark": [
		{
			"class_idx": 5,
			"name": "arrow",
			"points": [
				{
					"int_x": 15,
					"int_y": 270,
					"x": 0.0234375,
					"y": 0.5625
				},
				{
					"int_x": 153,
					"int_y": 270,
					"x": 0.2390625,
					"y": 0.5625
				},
				{
					"int_x": 153,
					"int_y": 379,
					"x": 0.2390625,
					"y": 0.7895833333333333
				},
				{
					"int_x": 15,
					"int_y": 379,
					"x": 0.0234375,
					"y": 0.7895833333333333
				}
			],
			"rect": {
				"h": 0.2270833333333333,
				"int_h": 110,
				"int_w": 139,
				"int_x": 15,
				"int_y": 270,
				"w": 0.215625,
				"x": 0.0234375,
				"y": 0.5625
			}
		}
	],
	"timestamp": 1640751003,
	"version": "1.5.30-1"
}
