{
	"completely_empty": false,
	"image": {
		"height": 480,
		"scale": 1.6458333333333333,
		"width": 640
	},
	"mark": [
		{
			"class_idx": 4,
			"name": "line",
			"points": [
				{
					"int_x": 255,
					"int_y": 68,
					"x": 0.3984375,
					"y": 0.14166666666666664
				},
				{
					"int_x": 345,
					"int_y": 68,
					"x": 0.5390625,
					"y": 0.14166666666666664
				},
				{
					"int_x": 345,
					"int_y": 179,
					"x": 0.5390625,
					"y": 0.3729166666666667
				},
				{
					"int_x": 255,
					"int_y": 179,
					"x": 0.3984375,
					"y": 0.3729166666666667
				}
			],
			"rect": {
				"h": 0.23125000000000004,
				"int_h": 112,
				"int_w": 91,
				"int_x": 255,
				"int_y": 68,
				"w": 0.140625,
				"x": 0.3984375,
				"y": 0.14166666666666664
			}
		}
	],
	"timestamp": 1640751003,
	"version": "1.5.30-1"
}
