{
	"completely_empty": false,
	"image": {
		"height": 480,
		"scale": 1.6458333333333333,
		"width": 640
	},
	"mark": [
		{
			"class_idx": 2,
			"name": "square",
			"points": [
				{
					"int_x": 141,
					"int_y": 72,
					"x": 0.22031250000000002,
					"y": 0.15000000000000002
				},
				{
					"int_x": 236,
					"int_y": 72,
					"x": 0.36875,
					"y": 0.15000000000000002
				},
				{
					"int_x": 236,
					"int_y": 167,
					"x": 0.36875,
					"y": 0.34791666666666665
				},
				{
					"int_x": 141,
					"int_y": 167,
					"x": 0.22031250000000002,
					"y": 0.34791666666666665
				}
			],
			"rect": {
				"h": 0.19791666666666663,
				"int_h": 96,
				"int_w": 96,
				"int_x": 141,
				"int_y": 72,
				"w": 0.1484375,
				"x": 0.22031250000000002,
				"y": 0.15000000000000002
			}
		}
	],
	"timestamp": 1640751003,
	"version": "1.5.30-1"
}
