{
	"completely_empty": false,
	"image": {
		"height": 480,
		"scale": 1.6458333333333333,
		"width": 640
	},
	"mark": [
		{
			"class_idx": 6,
			"name": "triangle",
			"points": [
				{
					"int_x": 392,
					"int_y": 295,
					"x": 0.6125,
					"y": 0.6145833333333334
				},
				{
					"int_x": 523,
					"int_y": 295,
					"x": 0.8171875,
					"y": 0.6145833333333334
				},
				{
					"int_x": 523,
					"int_y": 376,
					"x": 0.8171875,
					"y": 0.7833333333333333
				},
				{
					"int_x": 392,
					"int_y": 376,
					"x": 0.6125,
					"y": 0.7833333333333333
				}
			],
			"rect": {
				"h": 0.16874999999999996,
				"int_h": 82,
				"int_w": 132,
				"int_x": 392,
				"int_y": 295,
				"w": 0.2046874999999999,
				"x": 0.6125,
				"y": 0.6145833333333334
			}
		}
	],
	"timestamp": 1640751003,
	"version": "1.5.30-1"
}
