{
	"completely_empty": false,
	"image": {
		"height": 480,
		"scale": 1.6458333333333333,
		"width": 640
	},
	"mark": [
		{
			"class_idx": 5,
			"name": "arrow",
			"points": [
				{
					"int_x": 477,
					"int_y": 357,
					"x": 0.7453125,
					"y": 0.7437499999999999
				},
				{
					"int_x": 583,
					"int_y": 357,
					"x": 0.9109375,
					"y": 0.7437499999999999
				},
				{
					"int_x": 583,
					"int_y": 467,
					"x": 0.9109375,
					"y": 0.9729166666666667
				},
				{
					"int_x": 477,
					"int_y": 467,
					"x": 0.7453125,
					"y": 0.9729166666666667
				}
			],
			"rect": {
				"h": 0.22916666666666674,
				"int_h": 111,
				"int_w": 107,
				"int_x": 477,
				"int_y": 357,
				"w": 0.1656249999999999,
				"x": 0.7453125,
				"y": 0.7437499999999999
			}
		}
	],
	"timestamp": 1640750981,
	"version": "1.5.30-1"
}
