{
	"completely_empty": false,
	"image": {
		"height": 480,
		"scale": 1.6458333333333333,
		"width": 640
	},
	"mark": [
		{
			"class_idx": 3,
			"name": "rectangle",
			"points": [
				{
					"int_x": 24,
					"int_y": 110,
					"x": 0.037500000000000006,
					"y": 0.22916666666666666
				},
				{
					"int_x": 174,
					"int_y": 110,
					"x": 0.271875,
					"y": 0.22916666666666666
				},
				{
					"int_x": 174,
					"int_y": 191,
					"x": 0.271875,
					"y": 0.3979166666666667
				},
				{
					"int_x": 24,
					"int_y": 191,
					"x": 0.037500000000000006,
					"y": 0.3979166666666667
				}
			],
			"rect": {
				"h": 0.16875000000000004,
				"int_h": 82,
				"int_w": 151,
				"int_x": 24,
				"int_y": 110,
				"w": 0.23437499999999997,
				"x": 0.037500000000000006,
				"y": 0.22916666666666666
			}
		}
	],
	"timestamp": 1640750987,
	"version": "1.5.30-1"
}
