{
	"completely_empty": false,
	"image": {
		"height": 480,
		"scale": 1.6458333333333333,
		"width": 640
	},
	"mark": [
		{
			"class_idx": 3,
			"name": "rectangle",
			"points": [
				{
					"int_x": 419,
					"int_y": 331,
					"x": 0.6546875000000001,
					"y": 0.6895833333333333
				},
				{
					"int_x": 633,
					"int_y": 331,
					"x": 0.9890625,
					"y": 0.6895833333333333
				},
				{
					"int_x": 633,
					"int_y": 444,
					"x": 0.9890625,
					"y": 0.9249999999999999
				},
				{
					"int_x": 419,
					"int_y": 444,
					"x": 0.6546875000000001,
					"y": 0.9249999999999999
				}
			],
			"rect": {
				"h": 0.2354166666666666,
				"int_h": 114,
				"int_w": 215,
				"int_x": 419,
				"int_y": 331,
				"w": 0.33437499999999987,
				"x": 0.6546875000000001,
				"y": 0.6895833333333333
			}
		}
	],
	"timestamp": 1640750986,
	"version": "1.5.30-1"
}
