{
	"completely_empty": false,
	"image": {
		"height": 480,
		"scale": 1.6458333333333333,
		"width": 640
	},
	"mark": [
		{
			"class_idx": 5,
			"name": "arrow",
			"points": [
				{
					"int_x": 134,
					"int_y": 216,
					"x": 0.20937500000000003,
					"y": 0.45
				},
				{
					"int_x": 218,
					"int_y": 216,
					"x": 0.340625,
					"y": 0.45
				},
				{
					"int_x": 218,
					"int_y": 320,
					"x": 0.340625,
					"y": 0.6666666666666667
				},
				{
					"int_x": 134,
					"int_y": 320,
					"x": 0.20937500000000003,
					"y": 0.6666666666666667
				}
			],
			"rect": {
				"h": 0.21666666666666673,
				"int_h": 105,
				"int_w": 85,
				"int_x": 134,
				"int_y": 216,
				"w": 0.13124999999999998,
				"x": 0.20937500000000003,
				"y": 0.45
			}
		}
	],
	"timestamp": 1640750997,
	"version": "1.5.30-1"
}
