{
	"completely_empty": false,
	"image": {
		"height": 480,
		"scale": 1.6458333333333333,
		"width": 640
	},
	"mark": [
		{
			"class_idx": 0,
			"name": "ellipse",
			"points": [
				{
					"int_x": 281,
					"int_y": 9,
					"x": 0.43906249999999997,
					"y": 0.018750000000000003
				},
				{
					"int_x": 427,
					"int_y": 9,
					"x": 0.6671874999999999,
					"y": 0.018750000000000003
				},
				{
					"int_x": 427,
					"int_y": 88,
					"x": 0.6671874999999999,
					"y": 0.18333333333333335
				},
				{
					"int_x": 281,
					"int_y": 88,
					"x": 0.43906249999999997,
					"y": 0.18333333333333335
				}
			],
			"rect": {
				"h": 0.16458333333333336,
				"int_h": 80,
				"int_w": 147,
				"int_x": 281,
				"int_y": 9,
				"w": 0.22812499999999997,
				"x": 0.43906249999999997,
				"y": 0.018750000000000003
			}
		}
	],
	"timestamp": 1640750998,
	"version": "1.5.30-1"
}
