{
	"completely_empty": false,
	"image": {
		"height": 480,
		"scale": 1.6458333333333333,
		"width": 640
	},
	"mark": [
		{
			"class_idx": 2,
			"name": "square",
			"points": [
				{
					"int_x": 123,
					"int_y": 46,
					"x": 0.1921875,
					"y": 0.09583333333333334
				},
				{
					"int_x": 203,
					"int_y": 46,
					"x": 0.3171875,
					"y": 0.09583333333333334
				},
				{
					"int_x": 203,
					"int_y": 126,
					"x": 0.3171875,
					"y": 0.2625
				},
				{
					"int_x": 123,
					"int_y": 126,
					"x": 0.1921875,
					"y": 0.2625
				}
			],
			"rect": {
				"h": 0.16666666666666669,
				"int_h": 81,
				"int_w": 81,
				"int_x": 123,
				"int_y": 46,
				"w": 0.125,
				"x": 0.1921875,
				"y": 0.09583333333333334
			}
		}
	],
	"timestamp": 1640750998,
	"version": "1.5.30-1"
}
