{
	"completely_empty": false,
	"image": {
		"height": 480,
		"scale": 1.6458333333333333,
		"width": 640
	},
	"mark": [
		{
			"class_idx": 6,
			"name": "triangle",
			"points": [
				{
					"int_x": 389,
					"int_y": 193,
					"x": 0.6078125000000001,
					"y": 0.40208333333333335
				},
				{
					"int_x": 485,
					"int_y": 193,
					"x": 0.7578125,
					"y": 0.40208333333333335
				},
				{
					"int_x": 485,
					"int_y": 302,
					"x": 0.7578125,
					"y": 0.6291666666666667
				},
				{
					"int_x": 389,
					"int_y": 302,
					"x": 0.6078125000000001,
					"y": 0.6291666666666667
				}
			],
			"rect": {
				"h": 0.2270833333333333,
				"int_h": 110,
				"int_w": 97,
				"int_x": 389,
				"int_y": 193,
				"w": 0.1499999999999999,
				"x": 0.6078125000000001,
				"y": 0.40208333333333335
			}
		}
	],
	"timestamp": 1640750998,
	"version": "1.5.30-1"
}
