{
	"completely_empty": false,
	"image": {
		"height": 480,
		"scale": 1.6458333333333333,
		"width": 640
	},
	"mark": [
		{
			"class_idx": 5,
			"name": "arrow",
			"points": [
				{
					"int_x": 131,
					"int_y": 262,
					"x": 0.20468750000000002,
					"y": 0.5458333333333333
				},
				{
					"int_x": 220,
					"int_y": 262,
					"x": 0.34375,
					"y": 0.5458333333333333
				},
				{
					"int_x": 220,
					"int_y": 378,
					"x": 0.34375,
					"y": 0.7875
				},
				{
					"int_x": 131,
					"int_y": 378,
					"x": 0.20468750000000002,
					"y": 0.7875
				}
			],
			"rect": {
				"h": 0.2416666666666667,
				"int_h": 117,
				"int_w": 90,
				"int_x": 131,
				"int_y": 262,
				"w": 0.13906249999999998,
				"x": 0.20468750000000002,
				"y": 0.5458333333333333
			}
		}
	],
	"timestamp": 1640751004,
	"version": "1.5.30-1"
}
