{
	"completely_empty": false,
	"image": {
		"height": 480,
		"scale": 1.6458333333333333,
		"width": 640
	},
	"mark": [
		{
			"class_idx": 4,
			"name": "line",
			"points": [
				{
					"int_x": 138,
					"int_y": 365,
					"x": 0.215625,
					"y": 0.7604166666666667
				},
				{
					"int_x": 253,
					"int_y": 365,
					"x": 0.3953125,
					"y": 0.7604166666666667
				},
				{
					"int_x": 253,
					"int_y": 452,
					"x": 0.3953125,
					"y": 0.9416666666666667
				},
				{
					"int_x": 138,
					"int_y": 452,
					"x": 0.215625,
					"y": 0.9416666666666667
				}
			],
			"rect": {
				"h": 0.1812499999999999,
				"int_h": 88,
				"int_w": 116,
				"int_x": 138,
				"int_y": 365,
				"w": 0.1796875,
				"x": 0.215625,
				"y": 0.7604166666666667
			}
		}
	],
	"timestamp": 1640751005,
	"version": "1.5.30-1"
}
