{
	"completely_empty": false,
	"image": {
		"height": 480,
		"scale": 1.6458333333333333,
		"width": 640
	},
	"mark": [
		{
			"class_idx": 4,
			"name": "line",
			"points": [
				{
					"int_x": 13,
					"int_y": 89,
					"x": 0.02031250000000001,
					"y": 0.18541666666666667
				},
				{
					"int_x": 120,
					"int_y": 89,
					"x": 0.1875,
					"y": 0.18541666666666667
				},
				{
					"int_x": 120,
					"int_y": 196,
					"x": 0.1875,
					"y": 0.4083333333333333
				},
				{
					"int_x": 13,
					"int_y": 196,
					"x": 0.02031250000000001,
					"y": 0.4083333333333333
				}
			],
			"rect": {
				"h": 0.22291666666666665,
				"int_h": 108,
				"int_w": 108,
				"int_x": 13,
				"int_y": 89,
				"w": 0.1671875,
				"x": 0.02031250000000001,
				"y": 0.18541666666666667
			}
		}
	],
	"timestamp": 1640751005,
	"version": "1.5.30-1"
}
