{
	"completely_empty": false,
	"image": {
		"height": 480,
		"scale": 1.6458333333333333,
		"width": 640
	},
	"mark": [
		{
			"class_idx": 3,
			"name": "rectangle",
			"points": [
				{
					"int_x": 385,
					"int_y": 141,
					"x": 0.6015625,
					"y": 0.29375
				},
				{
					"int_x": 591,
					"int_y": 141,
					"x": 0.9234374999999999,
					"y": 0.29375
				},
				{
					"int_x": 591,
					"int_y": 250,
					"x": 0.9234374999999999,
					"y": 0.5208333333333334
				},
				{
					"int_x": 385,
					"int_y": 250,
					"x": 0.6015625,
					"y": 0.5208333333333334
				}
			],
			"rect": {
				"h": 0.22708333333333336,
				"int_h": 110,
				"int_w": 207,
				"int_x": 385,
				"int_y": 141,
				"w": 0.3218749999999999,
				"x": 0.6015625,
				"y": 0.29375
			}
		}
	],
	"timestamp": 1640751005,
	"version": "1.5.30-1"
}
