{
	"completely_empty": false,
	"image": {
		"height": 480,
		"scale": 1.6458333333333333,
		"width": 640
	},
	"mark": [
		{
			"class_idx": 2,
			"name": "square",
			"points": [
				{
					"int_x": 407,
					"int_y": 175,
					"x": 0.6359375,
					"y": 0.36458333333333337
				},
				{
					"int_x": 488,
					"int_y": 175,
					"x": 0.7625,
					"y": 0.36458333333333337
				},
				{
					"int_x": 488,
					"int_y": 256,
					"x": 0.7625,
					"y": 0.5333333333333333
				},
				{
					"int_x": 407,
					"int_y": 256,
					"x": 0.6359375,
					"y": 0.5333333333333333
				}
			],
			"rect": {
				"h": 0.16874999999999996,
				"int_h": 82,
				"int_w": 82,
				"int_x": 407,
				"int_y": 175,
				"w": 0.1265624999999999,
				"x": 0.6359375,
				"y": 0.36458333333333337
			}
		}
	],
	"timestamp": 1640751005,
	"version": "1.5.30-1"
}
