{
	"completely_empty": false,
	"image": {
		"height": 480,
		"scale": 1.6458333333333333,
		"width": 640
	},
	"mark": [
		{
			"class_idx": 5,
			"name": "arrow",
			"points": [
				{
					"int_x": 195,
					"int_y": 276,
					"x": 0.3046875,
					"y": 0.575
				},
				{
					"int_x": 320,
					"int_y": 276,
					"x": 0.5,
					"y": 0.575
				},
				{
					"int_x": 320,
					"int_y": 382,
					"x": 0.5,
					"y": 0.7958333333333334
				},
				{
					"int_x": 195,
					"int_y": 382,
					"x": 0.3046875,
					"y": 0.7958333333333334
				}
			],
			"rect": {
				"h": 0.22083333333333344,
				"int_h": 107,
				"int_w": 126,
				"int_x": 195,
				"int_y": 276,
				"w": 0.1953125,
				"x": 0.3046875,
				"y": 0.575
			}
		}
	],
	"timestamp": 1640751000,
	"version": "1.5.30-1"
}
