{
	"completely_empty": false,
	"image": {
		"height": 480,
		"scale": 1.6458333333333333,
		"width": 640
	},
	"mark": [
		{
			"class_idx": 1,
			"name": "circle",
			"points": [
				{
					"int_x": 180,
					"int_y": 308,
					"x": 0.28046875000000004,
					"y": 0.640625
				},
				{
					"int_x": 318,
					"int_y": 308,
					"x": 0.49609375,
					"y": 0.640625
				},
				{
					"int_x": 318,
					"int_y": 446,
					"x": 0.49609375,
					"y": 0.9281250000000001
				},
				{
					"int_x": 180,
					"int_y": 446,
					"x": 0.28046875000000004,
					"y": 0.9281250000000001
				}
			],
			"rect": {
				"h": 0.2875000000000001,
				"int_h": 139,
				"int_w": 139,
				"int_x": 180,
				"int_y": 308,
				"w": 0.21562499999999996,
				"x": 0.28046875000000004,
				"y": 0.640625
			}
		}
	],
	"timestamp": 1640751001,
	"version": "1.5.30-1"
}
