{
	"completely_empty": false,
	"image": {
		"height": 480,
		"scale": 1.6458333333333333,
		"width": 640
	},
	"mark": [
		{
			"class_idx": 1,
			"name": "circle",
			"points": [
				{
					"int_x": 6,
					"int_y": 91,
					"x": 0.010156249999999992,
					"y": 0.1885416666666667
				},
				{
					"int_x": 121,
					"int_y": 91,
					"x": 0.18828125,
					"y": 0.1885416666666667
				},
				{
					"int_x": 121,
					"int_y": 205,
					"x": 0.18828125,
					"y": 0.42604166666666665
				},
				{
					"int_x": 6,
					"int_y": 205,
					"x": 0.010156249999999992,
					"y": 0.42604166666666665
				}
			],
			"rect": {
				"h": 0.23749999999999996,
				"int_h": 115,
				"int_w": 116,
				"int_x": 6,
				"int_y": 91,
				"w": 0.17812500000000003,
				"x": 0.010156249999999992,
				"y": 0.1885416666666667
			}
		}
	],
	"timestamp": 1640751001,
	"version": "1.5.30-1"
}
