{
	"completely_empty": false,
	"image": {
		"height": 480,
		"scale": 1.6458333333333333,
		"width": 640
	},
	"mark": [
		{
			"class_idx": 3,
			"name": "rectangle",
			"points": [
				{
					"int_x": 49,
					"int_y": 169,
					"x": 0.0765625,
					"y": 0.3520833333333333
				},
				{
					"int_x": 199,
					"int_y": 169,
					"x": 0.3109375,
					"y": 0.3520833333333333
				},
				{
					"int_x": 199,
					"int_y": 250,
					"x": 0.3109375,
					"y": 0.5208333333333334
				},
				{
					"int_x": 49,
					"int_y": 250,
					"x": 0.0765625,
					"y": 0.5208333333333334
				}
			],
			"rect": {
				"h": 0.16875000000000007,
				"int_h": 82,
				"int_w": 151,
				"int_x": 49,
				"int_y": 169,
				"w": 0.23437499999999997,
				"x": 0.0765625,
				"y": 0.3520833333333333
			}
		}
	],
	"timestamp": 1640751002,
	"version": "1.5.30-1"
}
