{
	"completely_empty": false,
	"image": {
		"height": 480,
		"scale": 1.6458333333333333,
		"width": 640
	},
	"mark": [
		{
			"class_idx": 6,
			"name": "triangle",
			"points": [
				{
					"int_x": 10,
					"int_y": 182,
					"x": 0.015625,
					"y": 0.37916666666666665
				},
				{
					"int_x": 122,
					"int_y": 182,
					"x": 0.190625,
					"y": 0.37916666666666665
				},
				{
					"int_x": 122,
					"int_y": 260,
					"x": 0.190625,
					"y": 0.5416666666666666
				},
				{
					"int_x": 10,
					"int_y": 260,
					"x": 0.015625,
					"y": 0.5416666666666666
				}
			],
			"rect": {
				"h": 0.16249999999999998,
				"int_h": 79,
				"int_w": 113,
				"int_x": 10,
				"int_y": 182,
				"w": 0.175,
				"x": 0.015625,
				"y": 0.37916666666666665
			}
		}
	],
	"timestamp": 1640751002,
	"version": "1.5.30-1"
}
