{
	"completely_empty": false,
	"image": {
		"height": 480,
		"scale": 1.6458333333333333,
		"width": 640
	},
	"mark": [
		{
			"class_idx": 1,
			"name": "circle",
			"points": [
				{
					"int_x": 118,
					"int_y": 184,
					"x": 0.18359375000000003,
					"y": 0.38437499999999997
				},
				{
					"int_x": 220,
					"int_y": 184,
					"x": 0.34296875000000004,
					"y": 0.38437499999999997
				},
				{
					"int_x": 220,
					"int_y": 286,
					"x": 0.34296875000000004,
					"y": 0.5968749999999999
				},
				{
					"int_x": 118,
					"int_y": 286,
					"x": 0.18359375000000003,
					"y": 0.5968749999999999
				}
			],
			"rect": {
				"h": 0.21249999999999997,
				"int_h": 103,
				"int_w": 103,
				"int_x": 118,
				"int_y": 184,
				"w": 0.15937500000000002,
				"x": 0.18359375000000003,
				"y": 0.38437499999999997
			}
		}
	],
	"timestamp": 1640750976,
	"version": "1.5.30-1"
}
