{
	"completely_empty": false,
	"image": {
		"height": 480,
		"scale": 1.6458333333333333,
		"width": 640
	},
	"mark": [
		{
			"class_idx": 0,
			"name": "ellipse",
			"points": [
				{
					"int_x": 139,
					"int_y": 316,
					"x": 0.2171875,
					"y": 0.6583333333333333
				},
				{
					"int_x": 387,
					"int_y": 316,
					"x": 0.6046875,
					"y": 0.6583333333333333
				},
				{
					"int_x": 387,
					"int_y": 446,
					"x": 0.6046875,
					"y": 0.9291666666666666
				},
				{
					"int_x": 139,
					"int_y": 446,
					"x": 0.2171875,
					"y": 0.9291666666666666
				}
			],
			"rect": {
				"h": 0.27083333333333326,
				"int_h": 131,
				"int_w": 249,
				"int_x": 139,
				"int_y": 316,
				"w": 0.38750000000000007,
				"x": 0.2171875,
				"y": 0.6583333333333333
			}
		}
	],
	"timestamp": 1640750999,
	"version": "1.5.30-1"
}
