{
	"completely_empty": false,
	"image": {
		"height": 480,
		"scale": 1.6458333333333333,
		"width": 640
	},
	"mark": [
		{
			"class_idx": 0,
			"name": "ellipse",
			"points": [
				{
					"int_x": 241,
					"int_y": 94,
					"x": 0.3765625,
					"y": 0.19583333333333336
				},
				{
					"int_x": 503,
					"int_y": 94,
					"x": 0.7859375000000001,
					"y": 0.19583333333333336
				},
				{
					"int_x": 503,
					"int_y": 231,
					"x": 0.7859375000000001,
					"y": 0.48125
				},
				{
					"int_x": 241,
					"int_y": 231,
					"x": 0.3765625,
					"y": 0.48125
				}
			],
			"rect": {
				"h": 0.28541666666666665,
				"int_h": 138,
				"int_w": 263,
				"int_x": 241,
				"int_y": 94,
				"w": 0.40937500000000004,
				"x": 0.3765625,
				"y": 0.19583333333333336
			}
		}
	],
	"timestamp": 1640750999,
	"version": "1.5.30-1"
}
