{
	"completely_empty": false,
	"image": {
		"height": 480,
		"scale": 1.6458333333333333,
		"width": 640
	},
	"mark": [
		{
			"class_idx": 3,
			"name": "rectangle",
			"points": [
				{
					"int_x": 315,
					"int_y": 103,
					"x": 0.49218750000000006,
					"y": 0.21458333333333335
				},
				{
					"int_x": 579,
					"int_y": 103,
					"x": 0.9046875000000001,
					"y": 0.21458333333333335
				},
				{
					"int_x": 579,
					"int_y": 241,
					"x": 0.9046875000000001,
					"y": 0.5020833333333333
				},
				{
					"int_x": 315,
					"int_y": 241,
					"x": 0.49218750000000006,
					"y": 0.5020833333333333
				}
			],
			"rect": {
				"h": 0.2875,
				"int_h": 139,
				"int_w": 265,
				"int_x": 315,
				"int_y": 103,
				"w": 0.41250000000000003,
				"x": 0.49218750000000006,
				"y": 0.21458333333333335
			}
		}
	],
	"timestamp": 1640750999,
	"version": "1.5.30-1"
}
