{
	"completely_empty": false,
	"image": {
		"height": 480,
		"scale": 1.6458333333333333,
		"width": 640
	},
	"mark": [
		{
			"class_idx": 2,
			"name": "square",
			"points": [
				{
					"int_x": 233,
					"int_y": 195,
					"x": 0.3640625,
					"y": 0.40625000000000006
				},
				{
					"int_x": 328,
					"int_y": 195,
					"x": 0.5125,
					"y": 0.40625000000000006
				},
				{
					"int_x": 328,
					"int_y": 290,
					"x": 0.5125,
					"y": 0.6041666666666667
				},
				{
					"int_x": 233,
					"int_y": 290,
					"x": 0.3640625,
					"y": 0.6041666666666667
				}
			],
			"rect": {
				"h": 0.19791666666666669,
				"int_h": 96,
				"int_w": 96,
				"int_x": 233,
				"int_y": 195,
				"w": 0.14843749999999994,
				"x": 0.3640625,
				"y": 0.40625000000000006
			}
		}
	],
	"timestamp": 1640750999,
	"version": "1.5.30-1"
}
